cli/__init__.py
cli/cLI.py
quickping/__init__.py
quickping/base.py
quickping/color.py
quickping/error.py
quickping/quickping.py
quickping-1.3.0.dist-info/LICENSE
quickping-1.3.0.dist-info/METADATA
quickping-1.3.0.dist-info/WHEEL
quickping-1.3.0.dist-info/entry_points.txt
quickping-1.3.0.dist-info/top_level.txt
quickping-1.3.0.dist-info/RECORD
