Metadata-Version: 2.1
Name: quickping
Version: 1.3.0
Summary: Using Multi-Threads to find active IPv4 addresses
Home-page: https://github.com/sajjadlab/quickping.git
Author: Sajjad Jawad
Author-email: iamsajjad@mail.ru
License: Apache License 2.0
Platform: UNKNOWN
Classifier: Programming Language :: Python :: 3
Classifier: License :: OSI Approved :: Apache Software License
Classifier: Operating System :: OS Independent
Requires-Python: >=3.6
Requires-Dist: Click
